comfun/__init__.py
comfun/cryptography.py
comfun/data_generation.py
comfun/file_ops.py
comfun/geoloc.py
comfun/img_ops.py
comfun/math_ops.py
comfun/media.py
comfun/pdf_ops.py
comfun/stats.py
comfun/system.py
comfun/trigonometry.py
comfun/ukraine_reports.py
comfun-0.1.5.dist-info/METADATA
comfun-0.1.5.dist-info/WHEEL
comfun-0.1.5.dist-info/top_level.txt
comfun-0.1.5.dist-info/RECORD
