Metadata-Version: 2.1
Name: comfun
Version: 0.1.5
Summary: COMmonly used FUNctions
Home-page: 
Author: Roland Pfeiffer
Author-email: 
Requires-Dist: opencv-python
Requires-Dist: PyPDF2
Requires-Dist: wget
Requires-Dist: setuptools
